d8s_converters/__init__.py
d8s_converters/converter.py
d8s_converters/distance_converter.py
d8s_converters/temperature_converter.py
d8s_converters/time_converter.py
tests/__init__.py
tests/test_converter.py
tests/test_distance_converter.py
tests/test_temperature_converter.py
tests/test_time_converter.py
d8s_converters-0.8.0.dist-info/COPYING
d8s_converters-0.8.0.dist-info/COPYING.LESSER
d8s_converters-0.8.0.dist-info/METADATA
d8s_converters-0.8.0.dist-info/WHEEL
d8s_converters-0.8.0.dist-info/top_level.txt
d8s_converters-0.8.0.dist-info/zip-safe
d8s_converters-0.8.0.dist-info/RECORD
